anilibria/__init__.py
anilibria/__main__.py
anilibria_utils-0.2.0.dist-info/LICENSE.txt
anilibria_utils-0.2.0.dist-info/METADATA
anilibria_utils-0.2.0.dist-info/WHEEL
anilibria_utils-0.2.0.dist-info/top_level.txt
anilibria_utils-0.2.0.dist-info/RECORD
