Metadata-Version: 2.1
Name: anilibria-utils
Version: 0.2.0
Summary: download torrents from www.anilibria.tv
Home-page: https://github.com/Kolcha/anilibria-utils
Author: Nick Korotysh
Author-email: kolchaprogrammer@list.ru
License: MIT
Keywords: anime,torrent-downloader
Classifier: Intended Audience :: End Users/Desktop
Classifier: License :: OSI Approved :: MIT License
Classifier: Operating System :: OS Independent
Classifier: Programming Language :: Python :: 3
Classifier: Topic :: Internet
Requires-Python: >=3.6
License-File: LICENSE.txt
Requires-Dist: lxml
Requires-Dist: requests
